llm_evaluation_in_reasoning/app.py
llm_evaluation_in_reasoning/dataloader/__init__.py
llm_evaluation_in_reasoning/dataloader/base.py
llm_evaluation_in_reasoning/dataloader/gsm8k.py
llm_evaluation_in_reasoning/dataloader/gsm_symbolic.py
llm_evaluation_in_reasoning/dataloader/mmlu.py
llm_evaluation_in_reasoning/dataloader/putnam_axiom.py
llm_evaluation_in_reasoning/dataloader/simple_bench.py
llm_evaluation_in_reasoning/eval/__init__.py
llm_evaluation_in_reasoning/eval/model.py
llm_evaluation_in_reasoning/util/__init__.py
llm_evaluation_in_reasoning/util/putnam.py
llm_evaluation_in_reasoning/util/putnam_prompt.py
llm_evaluation_in_reasoning-1.4.2.dist-info/METADATA
llm_evaluation_in_reasoning-1.4.2.dist-info/WHEEL
llm_evaluation_in_reasoning-1.4.2.dist-info/entry_points.txt
llm_evaluation_in_reasoning-1.4.2.dist-info/licenses/LICENSE
llm_evaluation_in_reasoning-1.4.2.dist-info/RECORD
