Metadata-Version: 2.4
Name: llm_evaluation_in_reasoning
Version: 1.4.2
Summary: A project for evaluating reasoning capabilities in large language models (LLMs).
Author-email: Sheng Ren <rensheng0410@gamil.com>, Xiya Pang <sianing0531@gmail.com>
License: MIT License
License-File: LICENSE
Keywords: evaluation,llm,reasoning
Classifier: License :: OSI Approved :: MIT License
Classifier: Operating System :: OS Independent
Classifier: Programming Language :: Python :: 3
Classifier: Programming Language :: Python :: 3.11
Classifier: Programming Language :: Python :: 3.12
Requires-Python: >=3.11
Requires-Dist: datasets
Requires-Dist: fire
Requires-Dist: litellm==1.54.1
Requires-Dist: pathlib
Requires-Dist: python-dotenv
Requires-Dist: rich
Requires-Dist: sympy
